wrapmail/__init__.py
wrapmail/abstract_mail.py
wrapmail/abstract_sender.py
wrapmail/gmail/Gmail_Sender.py
wrapmail/gmail/Google.py
wrapmail/gmail/__init__.py
wrapmail/gmail/email.py
wrapmail/smtp/Smtp_Sender.py
wrapmail/smtp/__init__.py
wrapmail/smtp/email.py
wrapmail-0.0.2.dist-info/LICENSE
wrapmail-0.0.2.dist-info/METADATA
wrapmail-0.0.2.dist-info/WHEEL
wrapmail-0.0.2.dist-info/top_level.txt
wrapmail-0.0.2.dist-info/RECORD
