Metadata-Version: 2.1
Name: wrapmail
Version: 0.0.2
Summary: A package that helps to send emails through Python utilizing an OOP logic
Home-page: UNKNOWN
Author: Alperen Yıldız
Author-email: <alperenyildiz@sabanciuniv.edu
License: UNKNOWN
Keywords: python,mail,gmail,api,smtp
Platform: UNKNOWN
Classifier: Development Status :: 2 - Pre-Alpha
Classifier: Intended Audience :: Developers
Classifier: Programming Language :: Python :: 3
Classifier: Operating System :: Unix
Classifier: Operating System :: MacOS :: MacOS X
Classifier: Operating System :: Microsoft :: Windows
License-File: LICENSE
Requires-Dist: cachetools (==4.2.2)
Requires-Dist: certifi (==2021.5.30)
Requires-Dist: chardet (==4.0.0)
Requires-Dist: google-api-core (==1.30.0)
Requires-Dist: google-api-python-client (==2.12.0)
Requires-Dist: google-auth (==1.32.1)
Requires-Dist: google-auth-httplib2 (==0.1.0)
Requires-Dist: google-auth-oauthlib (==0.4.4)
Requires-Dist: googleapis-common-protos (==1.53.0)
Requires-Dist: httplib2 (==0.19.1)
Requires-Dist: idna (==2.10)
Requires-Dist: oauthlib (==3.1.1)
Requires-Dist: packaging (==21.0)
Requires-Dist: protobuf (==3.17.3)
Requires-Dist: pyasn1 (==0.4.8)
Requires-Dist: pyasn1-modules (==0.2.8)
Requires-Dist: pyparsing (==2.4.7)
Requires-Dist: pytz (==2021.1)
Requires-Dist: requests (==2.25.1)
Requires-Dist: requests-oauthlib (==1.3.0)
Requires-Dist: rsa (==4.7.2)
Requires-Dist: six (==1.16.0)
Requires-Dist: uritemplate (==3.0.1)
Requires-Dist: urllib3 (==1.26.6)
